foundrydeploy/__init__.py
foundrydeploy/__main__.py
foundrydeploy/const.py
foundrydeploy/deployer.py
foundrydeploy/log.py
foundrydeploy/parser.py
foundrydeploy-0.1.2.dist-info/METADATA
foundrydeploy-0.1.2.dist-info/WHEEL
foundrydeploy-0.1.2.dist-info/top_level.txt
foundrydeploy-0.1.2.dist-info/RECORD
